[
   {
      "url":"https://api.robinhood.com/positions/5QR16506/c0bb3aec-bd1e-471e-a4f0-ca011cbec711/",
      "symbol":"AMZN",
      "instrument":"https://api.robinhood.com/instruments/c0bb3aec-bd1e-471e-a4f0-ca011cbec711/",
      "account":"https://api.robinhood.com/accounts/5QR16506/",
      "account_number":"5QR16506",
      "average_buy_price":"2049.7214",
      "pending_average_buy_price":"2049.7214",
      "quantity":"6.33163100",
      "intraday_average_buy_price":"2918.9631",
      "intraday_quantity":"0.03919200",
      "shares_held_for_buys":"0.00000000",
      "shares_held_for_sells":"0.00000000",
      "shares_held_for_stock_grants":"0.00000000",
      "shares_held_for_options_collateral":"0.00000000",
      "shares_held_for_options_events":"0.00000000",
      "shares_pending_from_options_events":"0.00000000",
      "updated_at":"2020-07-24T13:47:12.236889Z",
      "created_at":"2016-10-28T14:37:09.465816Z"
   },
   {
      "url":"https://api.robinhood.com/positions/5QR16506/ebab2398-028d-4939-9f1d-13bf38f81c50/",
      "symbol":"FB",
      "instrument":"https://api.robinhood.com/instruments/ebab2398-028d-4939-9f1d-13bf38f81c50/",
      "account":"https://api.robinhood.com/accounts/5QR16506/",
      "account_number":"5QR16506",
      "average_buy_price":"234.4860",
      "pending_average_buy_price":"234.4860",
      "quantity":"12.59623500",
      "intraday_average_buy_price":"228.8785",
      "intraday_quantity":"0.47186600",
      "shares_held_for_buys":"0.00000000",
      "shares_held_for_sells":"0.00000000",
      "shares_held_for_stock_grants":"0.00000000",
      "shares_held_for_options_collateral":"0.00000000",
      "shares_held_for_options_events":"0.00000000",
      "shares_pending_from_options_events":"0.00000000",
      "updated_at":"2020-07-24T13:47:10.022807Z",
      "created_at":"2016-07-27T13:48:37.124151Z"
   },
   {
      "url":"https://api.robinhood.com/positions/5QR16506/3a47ca97-d5a2-4a55-9045-053a588894de/",
      "symbol":"TWTR",
      "instrument":"https://api.robinhood.com/instruments/3a47ca97-d5a2-4a55-9045-053a588894de/",
      "account":"https://api.robinhood.com/accounts/5QR16506/",
      "account_number":"5QR16506",
      "average_buy_price":"32.0549",
      "pending_average_buy_price":"32.0549",
      "quantity":"38.70786300",
      "intraday_average_buy_price":"37.6550",
      "intraday_quantity":"0.47802400",
      "shares_held_for_buys":"0.00000000",
      "shares_held_for_sells":"0.00000000",
      "shares_held_for_stock_grants":"0.00000000",
      "shares_held_for_options_collateral":"0.00000000",
      "shares_held_for_options_events":"0.00000000",
      "shares_pending_from_options_events":"0.00000000",
      "updated_at":"2020-07-24T13:49:18.616413Z",
      "created_at":"2015-04-28T14:40:35.234335Z"
   },
   {
      "url":"https://api.robinhood.com/positions/5QR16506/81733743-965a-4d93-b87a-6973cb9efd34/",
      "symbol":"NFLX",
      "instrument":"https://api.robinhood.com/instruments/81733743-965a-4d93-b87a-6973cb9efd34/",
      "account":"https://api.robinhood.com/accounts/5QR16506/",
      "account_number":"5QR16506",
      "average_buy_price":"458.1491",
      "pending_average_buy_price":"458.1491",
      "quantity":"6.64746300",
      "intraday_average_buy_price":"474.8810",
      "intraday_quantity":"0.21563300",
      "shares_held_for_buys":"0.00000000",
      "shares_held_for_sells":"0.00000000",
      "shares_held_for_stock_grants":"0.00000000",
      "shares_held_for_options_collateral":"0.00000000",
      "shares_held_for_options_events":"0.00000000",
      "shares_pending_from_options_events":"0.00000000",
      "updated_at":"2020-07-24T13:49:17.4451Z",
      "created_at":"2016-04-19T14:13:58.891831Z"
   },
   {
      "url":"https://api.robinhood.com/positions/5QR16506/943c5009-a0bb-4665-8cf4-a95dab5874e4/",
      "symbol":"GOOG",
      "instrument":"https://api.robinhood.com/instruments/943c5009-a0bb-4665-8cf4-a95dab5874e4/",
      "account":"https://api.robinhood.com/accounts/5QR16506/",
      "account_number":"5QR16506",
      "average_buy_price":"1482.1944",
      "pending_average_buy_price":"1482.1944",
      "quantity":"2.10390800",
      "intraday_average_buy_price":"1495.0093",
      "intraday_quantity":"0.06822700",
      "shares_held_for_buys":"0.00000000",
      "shares_held_for_sells":"0.00000000",
      "shares_held_for_stock_grants":"0.00000000",
      "shares_held_for_options_collateral":"0.00000000",
      "shares_held_for_options_events":"0.00000000",
      "shares_pending_from_options_events":"0.00000000",
      "updated_at":"2020-07-24T13:48:13.96136Z",
      "created_at":"2016-06-24T17:14:22.342604Z"
   },
   {
      "url":"https://api.robinhood.com/positions/5QR16506/68bae46a-c0a5-4cda-86a9-1d2460b0b7d3/",
      "symbol":"NEE",
      "instrument":"https://api.robinhood.com/instruments/68bae46a-c0a5-4cda-86a9-1d2460b0b7d3/",
      "account":"https://api.robinhood.com/accounts/5QR16506/",
      "account_number":"5QR16506",
      "average_buy_price":"215.5329",
      "pending_average_buy_price":"215.5329",
      "quantity":"4.31231800",
      "intraday_average_buy_price":"0.0000",
      "intraday_quantity":"0.00000000",
      "shares_held_for_buys":"0.00000000",
      "shares_held_for_sells":"0.00000000",
      "shares_held_for_stock_grants":"0.00000000",
      "shares_held_for_options_collateral":"0.00000000",
      "shares_held_for_options_events":"0.00000000",
      "shares_pending_from_options_events":"0.00000000",
      "updated_at":"2020-07-08T15:53:52.822673Z",
      "created_at":"2016-11-10T14:32:34.40192Z"
   },
   {
      "url":"https://api.robinhood.com/positions/5QR16506/50810c35-d215-4866-9758-0ada4ac79ffa/",
      "symbol":"MSFT",
      "instrument":"https://api.robinhood.com/instruments/50810c35-d215-4866-9758-0ada4ac79ffa/",
      "account":"https://api.robinhood.com/accounts/5QR16506/",
      "account_number":"5QR16506",
      "average_buy_price":"198.2982",
      "pending_average_buy_price":"198.2982",
      "quantity":"14.73203600",
      "intraday_average_buy_price":"199.0551",
      "intraday_quantity":"0.51242100",
      "shares_held_for_buys":"0.00000000",
      "shares_held_for_sells":"0.00000000",
      "shares_held_for_stock_grants":"0.00000000",
      "shares_held_for_options_collateral":"0.00000000",
      "shares_held_for_options_events":"0.00000000",
      "shares_pending_from_options_events":"0.00000000",
      "updated_at":"2020-07-24T13:49:17.165541Z",
      "created_at":"2015-04-10T17:26:50.294998Z"
   },
   {
      "url":"https://api.robinhood.com/positions/5QR16506/450dfc6d-5510-4d40-abfb-f633b7d9be3e/",
      "symbol":"AAPL",
      "instrument":"https://api.robinhood.com/instruments/450dfc6d-5510-4d40-abfb-f633b7d9be3e/",
      "account":"https://api.robinhood.com/accounts/5QR16506/",
      "account_number":"5QR16506",
      "average_buy_price":"361.3014",
      "pending_average_buy_price":"361.3014",
      "quantity":"8.06827500",
      "intraday_average_buy_price":"360.0169",
      "intraday_quantity":"0.28332000",
      "shares_held_for_buys":"0.00000000",
      "shares_held_for_sells":"0.00000000",
      "shares_held_for_stock_grants":"0.00000000",
      "shares_held_for_options_collateral":"0.00000000",
      "shares_held_for_options_events":"0.00000000",
      "shares_pending_from_options_events":"0.00000000",
      "updated_at":"2020-07-24T13:47:11.383013Z",
      "created_at":"2015-03-10T15:16:31.702552Z"
   },
   {
      "url":"https://api.robinhood.com/positions/5QR16506/e39ed23a-7bd1-4587-b060-71988d9ef483/",
      "symbol":"TSLA",
      "instrument":"https://api.robinhood.com/instruments/e39ed23a-7bd1-4587-b060-71988d9ef483/",
      "account":"https://api.robinhood.com/accounts/5QR16506/",
      "account_number":"5QR16506",
      "average_buy_price":"1188.2899",
      "pending_average_buy_price":"1188.2899",
      "quantity":"2.52159100",
      "intraday_average_buy_price":"1391.2789",
      "intraday_quantity":"0.08193900",
      "shares_held_for_buys":"0.00000000",
      "shares_held_for_sells":"0.00000000",
      "shares_held_for_stock_grants":"0.00000000",
      "shares_held_for_options_collateral":"0.00000000",
      "shares_held_for_options_events":"0.00000000",
      "shares_pending_from_options_events":"0.00000000",
      "updated_at":"2020-07-24T13:47:11.711687Z",
      "created_at":"2016-06-22T14:01:59.511191Z"
   },
   {
      "url":"https://api.robinhood.com/positions/5QR16506/b2e06903-5c44-46a4-bd42-2a696f9d68e1/",
      "symbol":"BABA",
      "instrument":"https://api.robinhood.com/instruments/b2e06903-5c44-46a4-bd42-2a696f9d68e1/",
      "account":"https://api.robinhood.com/accounts/5QR16506/",
      "account_number":"5QR16506",
      "average_buy_price":"251.5595",
      "pending_average_buy_price":"251.5595",
      "quantity":"1.40165600",
      "intraday_average_buy_price":"243.6478",
      "intraday_quantity":"0.07469800",
      "shares_held_for_buys":"0.00000000",
      "shares_held_for_sells":"0.00000000",
      "shares_held_for_stock_grants":"0.00000000",
      "shares_held_for_options_collateral":"0.00000000",
      "shares_held_for_options_events":"0.00000000",
      "shares_pending_from_options_events":"0.00000000",
      "updated_at":"2020-07-24T13:48:13.237919Z",
      "created_at":"2015-04-30T17:46:28.800651Z"
   },
   {
      "url":"https://api.robinhood.com/positions/5QR16506/f3acdd2f-6580-4c75-a69c-81481cc4c235/",
      "symbol":"SQ",
      "instrument":"https://api.robinhood.com/instruments/f3acdd2f-6580-4c75-a69c-81481cc4c235/",
      "account":"https://api.robinhood.com/accounts/5QR16506/",
      "account_number":"5QR16506",
      "average_buy_price":"102.0342",
      "pending_average_buy_price":"102.0342",
      "quantity":"24.35183000",
      "intraday_average_buy_price":"118.7747",
      "intraday_quantity":"0.40749400",
      "shares_held_for_buys":"0.00000000",
      "shares_held_for_sells":"0.00000000",
      "shares_held_for_stock_grants":"0.00000000",
      "shares_held_for_options_collateral":"0.00000000",
      "shares_held_for_options_events":"0.00000000",
      "shares_pending_from_options_events":"0.00000000",
      "updated_at":"2020-07-24T13:55:30.798842Z",
      "created_at":"2017-08-03T18:20:35.578432Z"
   },
   {
      "url":"https://api.robinhood.com/positions/5QR16506/940fc3f5-1db5-4fed-b452-f3a2e4562b5f/",
      "symbol":"AMD",
      "instrument":"https://api.robinhood.com/instruments/940fc3f5-1db5-4fed-b452-f3a2e4562b5f/",
      "account":"https://api.robinhood.com/accounts/5QR16506/",
      "account_number":"5QR16506",
      "average_buy_price":"54.6372",
      "pending_average_buy_price":"54.6372",
      "quantity":"28.42651800",
      "intraday_average_buy_price":"66.3485",
      "intraday_quantity":"0.27129500",
      "shares_held_for_buys":"0.00000000",
      "shares_held_for_sells":"0.00000000",
      "shares_held_for_stock_grants":"0.00000000",
      "shares_held_for_options_collateral":"0.00000000",
      "shares_held_for_options_events":"0.00000000",
      "shares_pending_from_options_events":"0.00000000",
      "updated_at":"2020-07-24T13:47:12.813112Z",
      "created_at":"2017-10-25T17:41:16.726422Z"
   },
   {
      "url":"https://api.robinhood.com/positions/5QR16506/417c652b-baba-4922-b903-8a0ec1dbc1d3/",
      "symbol":"HDB",
      "instrument":"https://api.robinhood.com/instruments/417c652b-baba-4922-b903-8a0ec1dbc1d3/",
      "account":"https://api.robinhood.com/accounts/5QR16506/",
      "account_number":"5QR16506",
      "average_buy_price":"44.2125",
      "pending_average_buy_price":"44.2125",
      "quantity":"60.35449000",
      "intraday_average_buy_price":"49.6600",
      "intraday_quantity":"0.36649200",
      "shares_held_for_buys":"0.00000000",
      "shares_held_for_sells":"0.00000000",
      "shares_held_for_stock_grants":"0.00000000",
      "shares_held_for_options_collateral":"0.00000000",
      "shares_held_for_options_events":"0.00000000",
      "shares_pending_from_options_events":"0.00000000",
      "updated_at":"2020-07-24T13:48:14.880606Z",
      "created_at":"2017-09-26T15:20:27.165222Z"
   },
   {
      "url":"https://api.robinhood.com/positions/5QR16506/3324b13c-dc23-40e8-8807-76d87fdb09ed/",
      "symbol":"CCL",
      "instrument":"https://api.robinhood.com/instruments/3324b13c-dc23-40e8-8807-76d87fdb09ed/",
      "account":"https://api.robinhood.com/accounts/5QR16506/",
      "account_number":"5QR16506",
      "average_buy_price":"14.7236",
      "pending_average_buy_price":"14.7236",
      "quantity":"4.75425200",
      "intraday_average_buy_price":"0.0000",
      "intraday_quantity":"0.00000000",
      "shares_held_for_buys":"0.00000000",
      "shares_held_for_sells":"0.00000000",
      "shares_held_for_stock_grants":"0.00000000",
      "shares_held_for_options_collateral":"0.00000000",
      "shares_held_for_options_events":"0.00000000",
      "shares_pending_from_options_events":"0.00000000",
      "updated_at":"2020-07-23T14:28:39.139947Z",
      "created_at":"2019-03-27T13:43:17.108316Z"
   },
   {
      "url":"https://api.robinhood.com/positions/5QR16506/a4ecd608-e7b4-4ff3-afa5-f77ae7632dfb/",
      "symbol":"NVDA",
      "instrument":"https://api.robinhood.com/instruments/a4ecd608-e7b4-4ff3-afa5-f77ae7632dfb/",
      "account":"https://api.robinhood.com/accounts/5QR16506/",
      "account_number":"5QR16506",
      "average_buy_price":"371.2222",
      "pending_average_buy_price":"371.2222",
      "quantity":"5.02507300",
      "intraday_average_buy_price":"396.9100",
      "intraday_quantity":"0.06097100",
      "shares_held_for_buys":"0.00000000",
      "shares_held_for_sells":"0.00000000",
      "shares_held_for_stock_grants":"0.00000000",
      "shares_held_for_options_collateral":"0.00000000",
      "shares_held_for_options_events":"0.00000000",
      "shares_pending_from_options_events":"0.00000000",
      "updated_at":"2020-07-24T13:47:11.802863Z",
      "created_at":"2017-05-09T17:39:51.087906Z"
   },
   {
      "url":"https://api.robinhood.com/positions/5QR16506/ae7f719c-ba1a-4207-8d94-af40fb7310f8/",
      "symbol":"BA",
      "instrument":"https://api.robinhood.com/instruments/ae7f719c-ba1a-4207-8d94-af40fb7310f8/",
      "account":"https://api.robinhood.com/accounts/5QR16506/",
      "account_number":"5QR16506",
      "average_buy_price":"176.4298",
      "pending_average_buy_price":"176.4298",
      "quantity":"2.03321700",
      "intraday_average_buy_price":"175.5451",
      "intraday_quantity":"1.24412500",
      "shares_held_for_buys":"0.00000000",
      "shares_held_for_sells":"0.00000000",
      "shares_held_for_stock_grants":"0.00000000",
      "shares_held_for_options_collateral":"0.00000000",
      "shares_held_for_options_events":"0.00000000",
      "shares_pending_from_options_events":"0.00000000",
      "updated_at":"2020-07-24T17:37:40.048498Z",
      "created_at":"2018-01-26T18:38:18.313658Z"
   },
   {
      "url":"https://api.robinhood.com/positions/5QR16506/091aac51-a092-4661-9920-2dbec9ca9d5b/",
      "symbol":"EADSY",
      "instrument":"https://api.robinhood.com/instruments/091aac51-a092-4661-9920-2dbec9ca9d5b/",
      "account":"https://api.robinhood.com/accounts/5QR16506/",
      "account_number":"5QR16506",
      "average_buy_price":"18.8588",
      "pending_average_buy_price":"18.8588",
      "quantity":"3.18153100",
      "intraday_average_buy_price":"0.0000",
      "intraday_quantity":"0.00000000",
      "shares_held_for_buys":"0.00000000",
      "shares_held_for_sells":"0.00000000",
      "shares_held_for_stock_grants":"0.00000000",
      "shares_held_for_options_collateral":"0.00000000",
      "shares_held_for_options_events":"0.00000000",
      "shares_pending_from_options_events":"0.00000000",
      "updated_at":"2020-07-23T14:28:36.863652Z",
      "created_at":"2020-06-04T18:46:30.421751Z"
   },
   {
      "url":"https://api.robinhood.com/positions/5QR16506/e140f07b-02f0-4299-9925-e8c59eaf0fe5/",
      "symbol":"JETS",
      "instrument":"https://api.robinhood.com/instruments/e140f07b-02f0-4299-9925-e8c59eaf0fe5/",
      "account":"https://api.robinhood.com/accounts/5QR16506/",
      "account_number":"5QR16506",
      "average_buy_price":"16.0400",
      "pending_average_buy_price":"16.0400",
      "quantity":"3.11720600",
      "intraday_average_buy_price":"0.0000",
      "intraday_quantity":"0.00000000",
      "shares_held_for_buys":"0.00000000",
      "shares_held_for_sells":"0.00000000",
      "shares_held_for_stock_grants":"0.00000000",
      "shares_held_for_options_collateral":"0.00000000",
      "shares_held_for_options_events":"0.00000000",
      "shares_pending_from_options_events":"0.00000000",
      "updated_at":"2020-07-23T14:28:39.342135Z",
      "created_at":"2020-06-04T18:47:27.686345Z"
   },
   {
      "url":"https://api.robinhood.com/positions/5QR16506/258dbaf2-8f3a-4fac-a40e-0b6f086e18c4/",
      "symbol":"SPR",
      "instrument":"https://api.robinhood.com/instruments/258dbaf2-8f3a-4fac-a40e-0b6f086e18c4/",
      "account":"https://api.robinhood.com/accounts/5QR16506/",
      "account_number":"5QR16506",
      "average_buy_price":"22.4242",
      "pending_average_buy_price":"22.4242",
      "quantity":"11.60354100",
      "intraday_average_buy_price":"22.3450",
      "intraday_quantity":"8.95054800",
      "shares_held_for_buys":"0.00000000",
      "shares_held_for_sells":"0.00000000",
      "shares_held_for_stock_grants":"0.00000000",
      "shares_held_for_options_collateral":"0.00000000",
      "shares_held_for_options_events":"0.00000000",
      "shares_pending_from_options_events":"0.00000000",
      "updated_at":"2020-07-24T17:37:57.256918Z",
      "created_at":"2020-06-04T18:47:09.336467Z"
   },
   {
      "url":"https://api.robinhood.com/positions/5QR16506/2a981efc-610f-4143-b2fb-b411659ba5a3/",
      "symbol":"STOR",
      "instrument":"https://api.robinhood.com/instruments/2a981efc-610f-4143-b2fb-b411659ba5a3/",
      "account":"https://api.robinhood.com/accounts/5QR16506/",
      "account_number":"5QR16506",
      "average_buy_price":"22.7276",
      "pending_average_buy_price":"22.7276",
      "quantity":"2.63996500",
      "intraday_average_buy_price":"0.0000",
      "intraday_quantity":"0.00000000",
      "shares_held_for_buys":"0.00000000",
      "shares_held_for_sells":"0.00000000",
      "shares_held_for_stock_grants":"0.00000000",
      "shares_held_for_options_collateral":"0.00000000",
      "shares_held_for_options_events":"0.00000000",
      "shares_pending_from_options_events":"0.00000000",
      "updated_at":"2020-07-23T14:28:39.745553Z",
      "created_at":"2020-06-04T19:05:26.592951Z"
   },
   {
      "url":"https://api.robinhood.com/positions/5QR16506/130d38bb-b38e-4613-82de-a9fa4e2dcfca/",
      "symbol":"MORT",
      "instrument":"https://api.robinhood.com/instruments/130d38bb-b38e-4613-82de-a9fa4e2dcfca/",
      "account":"https://api.robinhood.com/accounts/5QR16506/",
      "account_number":"5QR16506",
      "average_buy_price":"13.7400",
      "pending_average_buy_price":"13.7400",
      "quantity":"4.00291100",
      "intraday_average_buy_price":"0.0000",
      "intraday_quantity":"0.00000000",
      "shares_held_for_buys":"0.00000000",
      "shares_held_for_sells":"0.00000000",
      "shares_held_for_stock_grants":"0.00000000",
      "shares_held_for_options_collateral":"0.00000000",
      "shares_held_for_options_events":"0.00000000",
      "shares_pending_from_options_events":"0.00000000",
      "updated_at":"2020-07-23T14:28:38.726177Z",
      "created_at":"2020-06-04T18:52:13.218786Z"
   },
   {
      "url":"https://api.robinhood.com/positions/5QR16506/ecc706d4-d40f-413d-8a3d-55169be36121/",
      "symbol":"SPG",
      "instrument":"https://api.robinhood.com/instruments/ecc706d4-d40f-413d-8a3d-55169be36121/",
      "account":"https://api.robinhood.com/accounts/5QR16506/",
      "account_number":"5QR16506",
      "average_buy_price":"61.1267",
      "pending_average_buy_price":"61.1267",
      "quantity":"0.81797300",
      "intraday_average_buy_price":"0.0000",
      "intraday_quantity":"0.00000000",
      "shares_held_for_buys":"0.00000000",
      "shares_held_for_sells":"0.00000000",
      "shares_held_for_stock_grants":"0.00000000",
      "shares_held_for_options_collateral":"0.00000000",
      "shares_held_for_options_events":"0.00000000",
      "shares_pending_from_options_events":"0.00000000",
      "updated_at":"2020-07-23T14:28:39.883827Z",
      "created_at":"2020-06-04T19:18:29.073932Z"
   },
   {
      "url":"https://api.robinhood.com/positions/5QR16506/57aab0d9-7269-4ff2-954d-9dad6767784a/",
      "symbol":"SPCE",
      "instrument":"https://api.robinhood.com/instruments/57aab0d9-7269-4ff2-954d-9dad6767784a/",
      "account":"https://api.robinhood.com/accounts/5QR16506/",
      "account_number":"5QR16506",
      "average_buy_price":"24.9729",
      "pending_average_buy_price":"24.9729",
      "quantity":"5.64609600",
      "intraday_average_buy_price":"23.1700",
      "intraday_quantity":"1.30340900",
      "shares_held_for_buys":"0.00000000",
      "shares_held_for_sells":"0.00000000",
      "shares_held_for_stock_grants":"0.00000000",
      "shares_held_for_options_collateral":"0.00000000",
      "shares_held_for_options_events":"0.00000000",
      "shares_pending_from_options_events":"0.00000000",
      "updated_at":"2020-07-24T13:55:30.569693Z",
      "created_at":"2020-02-26T20:21:21.886838Z"
   },
   {
      "url":"https://api.robinhood.com/positions/5QR16506/72344724-c94c-4927-ab46-a0d80e31cb39/",
      "symbol":"MELI",
      "instrument":"https://api.robinhood.com/instruments/72344724-c94c-4927-ab46-a0d80e31cb39/",
      "account":"https://api.robinhood.com/accounts/5QR16506/",
      "account_number":"5QR16506",
      "average_buy_price":"948.3933",
      "pending_average_buy_price":"948.3933",
      "quantity":"3.10792500",
      "intraday_average_buy_price":"959.8357",
      "intraday_quantity":"0.05646800",
      "shares_held_for_buys":"0.00000000",
      "shares_held_for_sells":"0.00000000",
      "shares_held_for_stock_grants":"0.00000000",
      "shares_held_for_options_collateral":"0.00000000",
      "shares_held_for_options_events":"0.00000000",
      "shares_pending_from_options_events":"0.00000000",
      "updated_at":"2020-07-24T13:54:30.242869Z",
      "created_at":"2020-06-04T18:33:05.248568Z"
   },
   {
      "url":"https://api.robinhood.com/positions/5QR16506/9069774b-aa1e-49f1-8d8a-90459cab114b/",
      "symbol":"LVGO",
      "instrument":"https://api.robinhood.com/instruments/9069774b-aa1e-49f1-8d8a-90459cab114b/",
      "account":"https://api.robinhood.com/accounts/5QR16506/",
      "account_number":"5QR16506",
      "average_buy_price":"78.1891",
      "pending_average_buy_price":"78.1891",
      "quantity":"34.23040700",
      "intraday_average_buy_price":"102.9326",
      "intraday_quantity":"0.52655800",
      "shares_held_for_buys":"0.00000000",
      "shares_held_for_sells":"0.00000000",
      "shares_held_for_stock_grants":"0.00000000",
      "shares_held_for_options_collateral":"0.00000000",
      "shares_held_for_options_events":"0.00000000",
      "shares_pending_from_options_events":"0.00000000",
      "updated_at":"2020-07-24T13:54:26.898325Z",
      "created_at":"2020-06-04T18:33:30.75547Z"
   },
   {
      "url":"https://api.robinhood.com/positions/5QR16506/d05566bf-b0cc-414b-a520-b9216bb80abf/",
      "symbol":"SHOP",
      "instrument":"https://api.robinhood.com/instruments/d05566bf-b0cc-414b-a520-b9216bb80abf/",
      "account":"https://api.robinhood.com/accounts/5QR16506/",
      "account_number":"5QR16506",
      "average_buy_price":"875.8105",
      "pending_average_buy_price":"875.8105",
      "quantity":"2.69402400",
      "intraday_average_buy_price":"899.6851",
      "intraday_quantity":"0.04001400",
      "shares_held_for_buys":"0.00000000",
      "shares_held_for_sells":"0.00000000",
      "shares_held_for_stock_grants":"0.00000000",
      "shares_held_for_options_collateral":"0.00000000",
      "shares_held_for_options_events":"0.00000000",
      "shares_pending_from_options_events":"0.00000000",
      "updated_at":"2020-07-24T13:56:32.845578Z",
      "created_at":"2020-06-04T18:32:50.317842Z"
   },
   {
      "url":"https://api.robinhood.com/positions/5QR16506/f82f2908-cae3-4b06-86e2-28332a9bdfe3/",
      "symbol":"NOW",
      "instrument":"https://api.robinhood.com/instruments/f82f2908-cae3-4b06-86e2-28332a9bdfe3/",
      "account":"https://api.robinhood.com/accounts/5QR16506/",
      "account_number":"5QR16506",
      "average_buy_price":"400.7442",
      "pending_average_buy_price":"400.7442",
      "quantity":"3.46762500",
      "intraday_average_buy_price":"418.6912",
      "intraday_quantity":"0.11607600",
      "shares_held_for_buys":"0.00000000",
      "shares_held_for_sells":"0.00000000",
      "shares_held_for_stock_grants":"0.00000000",
      "shares_held_for_options_collateral":"0.00000000",
      "shares_held_for_options_events":"0.00000000",
      "shares_pending_from_options_events":"0.00000000",
      "updated_at":"2020-07-24T13:54:27.089742Z",
      "created_at":"2020-06-04T18:54:55.004874Z"
   },
   {
      "url":"https://api.robinhood.com/positions/5QR16506/57c966f5-ccbf-4ef6-a009-99c8bc318dd0/",
      "symbol":"CLDR",
      "instrument":"https://api.robinhood.com/instruments/57c966f5-ccbf-4ef6-a009-99c8bc318dd0/",
      "account":"https://api.robinhood.com/accounts/5QR16506/",
      "account_number":"5QR16506",
      "average_buy_price":"11.5943",
      "pending_average_buy_price":"11.5943",
      "quantity":"11.55052400",
      "intraday_average_buy_price":"11.2450",
      "intraday_quantity":"1.60071100",
      "shares_held_for_buys":"0.00000000",
      "shares_held_for_sells":"0.00000000",
      "shares_held_for_stock_grants":"0.00000000",
      "shares_held_for_options_collateral":"0.00000000",
      "shares_held_for_options_events":"0.00000000",
      "shares_pending_from_options_events":"0.00000000",
      "updated_at":"2020-07-24T13:44:51.921068Z",
      "created_at":"2020-06-05T15:18:35.759378Z"
   },
   {
      "url":"https://api.robinhood.com/positions/5QR16506/62d51e7b-7655-49da-b0fa-8d3496882fd4/",
      "symbol":"FSLY",
      "instrument":"https://api.robinhood.com/instruments/62d51e7b-7655-49da-b0fa-8d3496882fd4/",
      "account":"https://api.robinhood.com/accounts/5QR16506/",
      "account_number":"5QR16506",
      "average_buy_price":"68.0967",
      "pending_average_buy_price":"68.0967",
      "quantity":"31.85004200",
      "intraday_average_buy_price":"76.5802",
      "intraday_quantity":"0.31339700",
      "shares_held_for_buys":"0.00000000",
      "shares_held_for_sells":"0.00000000",
      "shares_held_for_stock_grants":"0.00000000",
      "shares_held_for_options_collateral":"0.00000000",
      "shares_held_for_options_events":"0.00000000",
      "shares_pending_from_options_events":"0.00000000",
      "updated_at":"2020-07-24T13:43:47.989059Z",
      "created_at":"2020-06-05T15:16:20.954944Z"
   },
   {
      "url":"https://api.robinhood.com/positions/5QR16506/d388bec4-921e-4ec2-b9f3-8f512c5b0484/",
      "symbol":"SE",
      "instrument":"https://api.robinhood.com/instruments/d388bec4-921e-4ec2-b9f3-8f512c5b0484/",
      "account":"https://api.robinhood.com/accounts/5QR16506/",
      "account_number":"5QR16506",
      "average_buy_price":"104.6461",
      "pending_average_buy_price":"104.6461",
      "quantity":"26.26812400",
      "intraday_average_buy_price":"102.8818",
      "intraday_quantity":"0.52681800",
      "shares_held_for_buys":"0.00000000",
      "shares_held_for_sells":"0.00000000",
      "shares_held_for_stock_grants":"0.00000000",
      "shares_held_for_options_collateral":"0.00000000",
      "shares_held_for_options_events":"0.00000000",
      "shares_pending_from_options_events":"0.00000000",
      "updated_at":"2020-07-24T13:54:27.677059Z",
      "created_at":"2020-06-04T18:33:17.056714Z"
   },
   {
      "url":"https://api.robinhood.com/positions/5QR16506/94ba5ec4-5f31-4640-b0a4-a8e93fbd2a31/",
      "symbol":"DXCM",
      "instrument":"https://api.robinhood.com/instruments/94ba5ec4-5f31-4640-b0a4-a8e93fbd2a31/",
      "account":"https://api.robinhood.com/accounts/5QR16506/",
      "account_number":"5QR16506",
      "average_buy_price":"385.0900",
      "pending_average_buy_price":"385.0900",
      "quantity":"3.62698100",
      "intraday_average_buy_price":"407.7541",
      "intraday_quantity":"0.05885900",
      "shares_held_for_buys":"0.00000000",
      "shares_held_for_sells":"0.00000000",
      "shares_held_for_stock_grants":"0.00000000",
      "shares_held_for_options_collateral":"0.00000000",
      "shares_held_for_options_events":"0.00000000",
      "shares_pending_from_options_events":"0.00000000",
      "updated_at":"2020-07-24T13:43:47.687132Z",
      "created_at":"2020-06-04T19:49:35.148482Z"
   },
   {
      "url":"https://api.robinhood.com/positions/5QR16506/9f1399e5-5023-425a-9eb5-cd3f91560189/",
      "symbol":"NIO",
      "instrument":"https://api.robinhood.com/instruments/9f1399e5-5023-425a-9eb5-cd3f91560189/",
      "account":"https://api.robinhood.com/accounts/5QR16506/",
      "account_number":"5QR16506",
      "average_buy_price":"6.8190",
      "pending_average_buy_price":"6.8190",
      "quantity":"48.39409900",
      "intraday_average_buy_price":"10.9672",
      "intraday_quantity":"4.55905100",
      "shares_held_for_buys":"0.00000000",
      "shares_held_for_sells":"0.00000000",
      "shares_held_for_stock_grants":"0.00000000",
      "shares_held_for_options_collateral":"0.00000000",
      "shares_held_for_options_events":"0.00000000",
      "shares_pending_from_options_events":"0.00000000",
      "updated_at":"2020-07-24T13:52:41.639083Z",
      "created_at":"2020-03-04T15:36:46.7917Z"
   },
   {
      "url":"https://api.robinhood.com/positions/5QR16506/ad059c69-0c1c-4c6b-8322-f53f1bbd69d4/",
      "symbol":"INTC",
      "instrument":"https://api.robinhood.com/instruments/ad059c69-0c1c-4c6b-8322-f53f1bbd69d4/",
      "account":"https://api.robinhood.com/accounts/5QR16506/",
      "account_number":"5QR16506",
      "average_buy_price":"56.4220",
      "pending_average_buy_price":"56.4220",
      "quantity":"12.62451500",
      "intraday_average_buy_price":"49.9351",
      "intraday_quantity":"0.36046800",
      "shares_held_for_buys":"0.00000000",
      "shares_held_for_sells":"0.00000000",
      "shares_held_for_stock_grants":"0.00000000",
      "shares_held_for_options_collateral":"0.00000000",
      "shares_held_for_options_events":"0.00000000",
      "shares_pending_from_options_events":"0.00000000",
      "updated_at":"2020-07-24T13:48:15.483718Z",
      "created_at":"2015-06-26T19:18:46.672514Z"
   },
   {
      "url":"https://api.robinhood.com/positions/5QR16506/309344d3-af67-4190-9970-b10618959fe5/",
      "symbol":"PYPL",
      "instrument":"https://api.robinhood.com/instruments/309344d3-af67-4190-9970-b10618959fe5/",
      "account":"https://api.robinhood.com/accounts/5QR16506/",
      "account_number":"5QR16506",
      "average_buy_price":"165.3467",
      "pending_average_buy_price":"165.3467",
      "quantity":"8.47144100",
      "intraday_average_buy_price":"170.5208",
      "intraday_quantity":"0.10555900",
      "shares_held_for_buys":"0.00000000",
      "shares_held_for_sells":"0.00000000",
      "shares_held_for_stock_grants":"0.00000000",
      "shares_held_for_options_collateral":"0.00000000",
      "shares_held_for_options_events":"0.00000000",
      "shares_pending_from_options_events":"0.00000000",
      "updated_at":"2020-07-24T13:49:17.753897Z",
      "created_at":"2020-06-08T16:06:11.248594Z"
   },
   {
      "url":"https://api.robinhood.com/positions/5QR16506/a03a6b8f-6a84-4219-bb21-a215ffbcb73e/",
      "symbol":"LOW",
      "instrument":"https://api.robinhood.com/instruments/a03a6b8f-6a84-4219-bb21-a215ffbcb73e/",
      "account":"https://api.robinhood.com/accounts/5QR16506/",
      "account_number":"5QR16506",
      "average_buy_price":"146.2557",
      "pending_average_buy_price":"146.2557",
      "quantity":"1.05773700",
      "intraday_average_buy_price":"146.2352",
      "intraday_quantity":"0.12445700",
      "shares_held_for_buys":"0.00000000",
      "shares_held_for_sells":"0.00000000",
      "shares_held_for_stock_grants":"0.00000000",
      "shares_held_for_options_collateral":"0.00000000",
      "shares_held_for_options_events":"0.00000000",
      "shares_pending_from_options_events":"0.00000000",
      "updated_at":"2020-07-24T13:48:15.709044Z",
      "created_at":"2017-06-08T14:40:23.297125Z"
   },
   {
      "url":"https://api.robinhood.com/positions/5QR16506/93495afe-b84b-4664-881c-b6361b0edeef/",
      "symbol":"V",
      "instrument":"https://api.robinhood.com/instruments/93495afe-b84b-4664-881c-b6361b0edeef/",
      "account":"https://api.robinhood.com/accounts/5QR16506/",
      "account_number":"5QR16506",
      "average_buy_price":"194.6055",
      "pending_average_buy_price":"194.6055",
      "quantity":"7.36573600",
      "intraday_average_buy_price":"195.1156",
      "intraday_quantity":"0.12300400",
      "shares_held_for_buys":"0.00000000",
      "shares_held_for_sells":"0.00000000",
      "shares_held_for_stock_grants":"0.00000000",
      "shares_held_for_options_collateral":"0.00000000",
      "shares_held_for_options_events":"0.00000000",
      "shares_pending_from_options_events":"0.00000000",
      "updated_at":"2020-07-24T13:47:11.536274Z",
      "created_at":"2019-05-07T17:46:13.485129Z"
   },
   {
      "url":"https://api.robinhood.com/positions/5QR16506/62f7b2b4-3c95-457a-a5ef-9efc6f7ccf75/",
      "symbol":"SMH",
      "instrument":"https://api.robinhood.com/instruments/62f7b2b4-3c95-457a-a5ef-9efc6f7ccf75/",
      "account":"https://api.robinhood.com/accounts/5QR16506/",
      "account_number":"5QR16506",
      "average_buy_price":"153.0240",
      "pending_average_buy_price":"153.0240",
      "quantity":"19.77129100",
      "intraday_average_buy_price":"158.5452",
      "intraday_quantity":"0.69507000",
      "shares_held_for_buys":"0.00000000",
      "shares_held_for_sells":"0.00000000",
      "shares_held_for_stock_grants":"0.00000000",
      "shares_held_for_options_collateral":"0.00000000",
      "shares_held_for_options_events":"0.00000000",
      "shares_pending_from_options_events":"0.00000000",
      "updated_at":"2020-07-24T13:51:39.364514Z",
      "created_at":"2020-06-04T18:21:06.77416Z"
   },
   {
      "url":"https://api.robinhood.com/positions/5QR16506/6c15195b-fcd7-4a57-8e3c-232e158e5904/",
      "symbol":"VGT",
      "instrument":"https://api.robinhood.com/instruments/6c15195b-fcd7-4a57-8e3c-232e158e5904/",
      "account":"https://api.robinhood.com/accounts/5QR16506/",
      "account_number":"5QR16506",
      "average_buy_price":"285.7084",
      "pending_average_buy_price":"285.7084",
      "quantity":"5.36809600",
      "intraday_average_buy_price":"278.6175",
      "intraday_quantity":"0.84488600",
      "shares_held_for_buys":"0.00000000",
      "shares_held_for_sells":"0.00000000",
      "shares_held_for_stock_grants":"0.00000000",
      "shares_held_for_options_collateral":"0.00000000",
      "shares_held_for_options_events":"0.00000000",
      "shares_pending_from_options_events":"0.00000000",
      "updated_at":"2020-07-24T13:51:44.385365Z",
      "created_at":"2019-10-21T15:47:37.803083Z"
   },
   {
      "url":"https://api.robinhood.com/positions/5QR16506/1be45236-6701-4d7e-af84-48dac3628879/",
      "symbol":"VUG",
      "instrument":"https://api.robinhood.com/instruments/1be45236-6701-4d7e-af84-48dac3628879/",
      "account":"https://api.robinhood.com/accounts/5QR16506/",
      "account_number":"5QR16506",
      "average_buy_price":"212.2333",
      "pending_average_buy_price":"212.2333",
      "quantity":"6.51094600",
      "intraday_average_buy_price":"208.3419",
      "intraday_quantity":"1.12891400",
      "shares_held_for_buys":"0.00000000",
      "shares_held_for_sells":"0.00000000",
      "shares_held_for_stock_grants":"0.00000000",
      "shares_held_for_options_collateral":"0.00000000",
      "shares_held_for_options_events":"0.00000000",
      "shares_pending_from_options_events":"0.00000000",
      "updated_at":"2020-07-24T13:51:40.193908Z",
      "created_at":"2020-06-04T18:20:35.505325Z"
   },
   {
      "url":"https://api.robinhood.com/positions/5QR16506/8373dfad-6a18-481e-a6da-b6d754fa7937/",
      "symbol":"MA",
      "instrument":"https://api.robinhood.com/instruments/8373dfad-6a18-481e-a6da-b6d754fa7937/",
      "account":"https://api.robinhood.com/accounts/5QR16506/",
      "account_number":"5QR16506",
      "average_buy_price":"309.8332",
      "pending_average_buy_price":"309.8332",
      "quantity":"0.48900500",
      "intraday_average_buy_price":"306.2581",
      "intraday_quantity":"0.05942700",
      "shares_held_for_buys":"0.00000000",
      "shares_held_for_sells":"0.00000000",
      "shares_held_for_stock_grants":"0.00000000",
      "shares_held_for_options_collateral":"0.00000000",
      "shares_held_for_options_events":"0.00000000",
      "shares_pending_from_options_events":"0.00000000",
      "updated_at":"2020-07-24T13:49:16.57713Z",
      "created_at":"2020-06-08T16:06:51.84595Z"
   },
   {
      "url":"https://api.robinhood.com/positions/5QR16506/5dd80664-c4ff-403e-aae8-5e9d2d074595/",
      "symbol":"WCLD",
      "instrument":"https://api.robinhood.com/instruments/5dd80664-c4ff-403e-aae8-5e9d2d074595/",
      "account":"https://api.robinhood.com/accounts/5QR16506/",
      "account_number":"5QR16506",
      "average_buy_price":"39.8723",
      "pending_average_buy_price":"39.8723",
      "quantity":"26.50381400",
      "intraday_average_buy_price":"38.7308",
      "intraday_quantity":"4.52353700",
      "shares_held_for_buys":"0.00000000",
      "shares_held_for_sells":"0.00000000",
      "shares_held_for_stock_grants":"0.00000000",
      "shares_held_for_options_collateral":"0.00000000",
      "shares_held_for_options_events":"0.00000000",
      "shares_pending_from_options_events":"0.00000000",
      "updated_at":"2020-07-24T13:36:18.628649Z",
      "created_at":"2020-06-04T17:40:08.426639Z"
   },
   {
      "url":"https://api.robinhood.com/positions/5QR16506/35875944-ffb7-47eb-a2e5-582ba9f26a8d/",
      "symbol":"ZM",
      "instrument":"https://api.robinhood.com/instruments/35875944-ffb7-47eb-a2e5-582ba9f26a8d/",
      "account":"https://api.robinhood.com/accounts/5QR16506/",
      "account_number":"5QR16506",
      "average_buy_price":"253.9740",
      "pending_average_buy_price":"253.9740",
      "quantity":"1.20760400",
      "intraday_average_buy_price":"241.4409",
      "intraday_quantity":"0.17478400",
      "shares_held_for_buys":"0.00000000",
      "shares_held_for_sells":"0.00000000",
      "shares_held_for_stock_grants":"0.00000000",
      "shares_held_for_options_collateral":"0.00000000",
      "shares_held_for_options_events":"0.00000000",
      "shares_pending_from_options_events":"0.00000000",
      "updated_at":"2020-07-24T13:55:31.4171Z",
      "created_at":"2020-06-08T13:38:47.766368Z"
   },
   {
      "url":"https://api.robinhood.com/positions/5QR16506/43c1172a-9130-420a-ac9b-b01a6ff5dd54/",
      "symbol":"JPM",
      "instrument":"https://api.robinhood.com/instruments/43c1172a-9130-420a-ac9b-b01a6ff5dd54/",
      "account":"https://api.robinhood.com/accounts/5QR16506/",
      "account_number":"5QR16506",
      "average_buy_price":"98.6392",
      "pending_average_buy_price":"98.6392",
      "quantity":"2.57605300",
      "intraday_average_buy_price":"98.7650",
      "intraday_quantity":"0.68850300",
      "shares_held_for_buys":"0.00000000",
      "shares_held_for_sells":"0.00000000",
      "shares_held_for_stock_grants":"0.00000000",
      "shares_held_for_options_collateral":"0.00000000",
      "shares_held_for_options_events":"0.00000000",
      "shares_pending_from_options_events":"0.00000000",
      "updated_at":"2020-07-24T14:51:05.483823Z",
      "created_at":"2015-03-10T15:15:12.384612Z"
   },
   {
      "url":"https://api.robinhood.com/positions/5QR16506/18006bfb-cbad-4326-8348-738c94ea47fa/",
      "symbol":"AMAT",
      "instrument":"https://api.robinhood.com/instruments/18006bfb-cbad-4326-8348-738c94ea47fa/",
      "account":"https://api.robinhood.com/accounts/5QR16506/",
      "account_number":"5QR16506",
      "average_buy_price":"63.3187",
      "pending_average_buy_price":"63.3187",
      "quantity":"2.41950400",
      "intraday_average_buy_price":"60.4400",
      "intraday_quantity":"0.29781600",
      "shares_held_for_buys":"0.00000000",
      "shares_held_for_sells":"0.00000000",
      "shares_held_for_stock_grants":"0.00000000",
      "shares_held_for_options_collateral":"0.00000000",
      "shares_held_for_options_events":"0.00000000",
      "shares_pending_from_options_events":"0.00000000",
      "updated_at":"2020-07-24T13:47:12.577905Z",
      "created_at":"2015-04-27T14:40:35.816496Z"
   },
   {
      "url":"https://api.robinhood.com/positions/5QR16506/599dd133-44d3-4c1e-b992-eb08b7ab7faa/",
      "symbol":"HD",
      "instrument":"https://api.robinhood.com/instruments/599dd133-44d3-4c1e-b992-eb08b7ab7faa/",
      "account":"https://api.robinhood.com/accounts/5QR16506/",
      "account_number":"5QR16506",
      "average_buy_price":"263.4607",
      "pending_average_buy_price":"263.4607",
      "quantity":"0.57959300",
      "intraday_average_buy_price":"264.3735",
      "intraday_quantity":"0.06884200",
      "shares_held_for_buys":"0.00000000",
      "shares_held_for_sells":"0.00000000",
      "shares_held_for_stock_grants":"0.00000000",
      "shares_held_for_options_collateral":"0.00000000",
      "shares_held_for_options_events":"0.00000000",
      "shares_pending_from_options_events":"0.00000000",
      "updated_at":"2020-07-24T13:48:14.31451Z",
      "created_at":"2017-07-25T13:57:45.207678Z"
   },
   {
      "url":"https://api.robinhood.com/positions/5QR16506/a20890a5-68c7-4e5e-8884-ed09673d7f80/",
      "symbol":"NOBL",
      "instrument":"https://api.robinhood.com/instruments/a20890a5-68c7-4e5e-8884-ed09673d7f80/",
      "account":"https://api.robinhood.com/accounts/5QR16506/",
      "account_number":"5QR16506",
      "average_buy_price":"71.0832",
      "pending_average_buy_price":"71.0832",
      "quantity":"10.21240200",
      "intraday_average_buy_price":"71.2850",
      "intraday_quantity":"1.75352400",
      "shares_held_for_buys":"0.00000000",
      "shares_held_for_sells":"0.00000000",
      "shares_held_for_stock_grants":"0.00000000",
      "shares_held_for_options_collateral":"0.00000000",
      "shares_held_for_options_events":"0.00000000",
      "shares_pending_from_options_events":"0.00000000",
      "updated_at":"2020-07-24T13:36:17.402207Z",
      "created_at":"2020-06-08T13:37:32.484721Z"
   },
   {
      "url":"https://api.robinhood.com/positions/5QR16506/ca21761c-1217-4e6e-9f63-4c9d43daf9ac/",
      "symbol":"LRCX",
      "instrument":"https://api.robinhood.com/instruments/ca21761c-1217-4e6e-9f63-4c9d43daf9ac/",
      "account":"https://api.robinhood.com/accounts/5QR16506/",
      "account_number":"5QR16506",
      "average_buy_price":"353.9839",
      "pending_average_buy_price":"353.9839",
      "quantity":"0.39693900",
      "intraday_average_buy_price":"338.0261",
      "intraday_quantity":"0.05384200",
      "shares_held_for_buys":"0.00000000",
      "shares_held_for_sells":"0.00000000",
      "shares_held_for_stock_grants":"0.00000000",
      "shares_held_for_options_collateral":"0.00000000",
      "shares_held_for_options_events":"0.00000000",
      "shares_pending_from_options_events":"0.00000000",
      "updated_at":"2020-07-24T13:49:16.283372Z",
      "created_at":"2018-01-25T14:54:32.268337Z"
   },
   {
      "url":"https://api.robinhood.com/positions/5QR16506/1abfbfc7-6c65-4ded-8a97-1e7f82220b64/",
      "symbol":"UNH",
      "instrument":"https://api.robinhood.com/instruments/1abfbfc7-6c65-4ded-8a97-1e7f82220b64/",
      "account":"https://api.robinhood.com/accounts/5QR16506/",
      "account_number":"5QR16506",
      "average_buy_price":"304.3249",
      "pending_average_buy_price":"304.3249",
      "quantity":"0.51264300",
      "intraday_average_buy_price":"302.6787",
      "intraday_quantity":"0.05946900",
      "shares_held_for_buys":"0.00000000",
      "shares_held_for_sells":"0.00000000",
      "shares_held_for_stock_grants":"0.00000000",
      "shares_held_for_options_collateral":"0.00000000",
      "shares_held_for_options_events":"0.00000000",
      "shares_pending_from_options_events":"0.00000000",
      "updated_at":"2020-07-24T13:49:18.971812Z",
      "created_at":"2019-04-17T14:37:09.080092Z"
   },
   {
      "url":"https://api.robinhood.com/positions/5QR16506/a1d81375-4b0c-4902-8285-03c011726297/",
      "symbol":"TDOC",
      "instrument":"https://api.robinhood.com/instruments/a1d81375-4b0c-4902-8285-03c011726297/",
      "account":"https://api.robinhood.com/accounts/5QR16506/",
      "account_number":"5QR16506",
      "average_buy_price":"221.1654",
      "pending_average_buy_price":"221.1654",
      "quantity":"0.66108900",
      "intraday_average_buy_price":"211.0274",
      "intraday_quantity":"0.08529700",
      "shares_held_for_buys":"0.00000000",
      "shares_held_for_sells":"0.00000000",
      "shares_held_for_stock_grants":"0.00000000",
      "shares_held_for_options_collateral":"0.00000000",
      "shares_held_for_options_events":"0.00000000",
      "shares_pending_from_options_events":"0.00000000",
      "updated_at":"2020-07-24T13:45:56.858453Z",
      "created_at":"2020-06-08T13:38:48.311207Z"
   },
   {
      "url":"https://api.robinhood.com/positions/5QR16506/efc990f3-ac30-4a4e-8a90-bd1c63501983/",
      "symbol":"DOCU",
      "instrument":"https://api.robinhood.com/instruments/efc990f3-ac30-4a4e-8a90-bd1c63501983/",
      "account":"https://api.robinhood.com/accounts/5QR16506/",
      "account_number":"5QR16506",
      "average_buy_price":"199.1807",
      "pending_average_buy_price":"199.1807",
      "quantity":"1.58655000",
      "intraday_average_buy_price":"189.0021",
      "intraday_quantity":"0.22327800",
      "shares_held_for_buys":"0.00000000",
      "shares_held_for_sells":"0.00000000",
      "shares_held_for_stock_grants":"0.00000000",
      "shares_held_for_options_collateral":"0.00000000",
      "shares_held_for_options_events":"0.00000000",
      "shares_pending_from_options_events":"0.00000000",
      "updated_at":"2020-07-24T13:55:29.288481Z",
      "created_at":"2020-06-08T13:38:49.132645Z"
   },
   {
      "url":"https://api.robinhood.com/positions/5QR16506/417571a0-be77-475e-a15f-411fd4b1d79f/",
      "symbol":"DDOG",
      "instrument":"https://api.robinhood.com/instruments/417571a0-be77-475e-a15f-411fd4b1d79f/",
      "account":"https://api.robinhood.com/accounts/5QR16506/",
      "account_number":"5QR16506",
      "average_buy_price":"85.8799",
      "pending_average_buy_price":"85.8799",
      "quantity":"6.89451700",
      "intraday_average_buy_price":"82.6238",
      "intraday_quantity":"0.65598500",
      "shares_held_for_buys":"0.00000000",
      "shares_held_for_sells":"0.00000000",
      "shares_held_for_stock_grants":"0.00000000",
      "shares_held_for_options_collateral":"0.00000000",
      "shares_held_for_options_events":"0.00000000",
      "shares_pending_from_options_events":"0.00000000",
      "updated_at":"2020-07-24T13:54:30.769962Z",
      "created_at":"2020-05-27T14:59:11.603066Z"
   },
   {
      "url":"https://api.robinhood.com/positions/5QR16506/bc06e768-0955-49f2-ab45-2e07cab0fbe2/",
      "symbol":"TEAM",
      "instrument":"https://api.robinhood.com/instruments/bc06e768-0955-49f2-ab45-2e07cab0fbe2/",
      "account":"https://api.robinhood.com/accounts/5QR16506/",
      "account_number":"5QR16506",
      "average_buy_price":"190.1176",
      "pending_average_buy_price":"190.1176",
      "quantity":"1.12072700",
      "intraday_average_buy_price":"182.1302",
      "intraday_quantity":"0.13287200",
      "shares_held_for_buys":"0.00000000",
      "shares_held_for_sells":"0.00000000",
      "shares_held_for_stock_grants":"0.00000000",
      "shares_held_for_options_collateral":"0.00000000",
      "shares_held_for_options_events":"0.00000000",
      "shares_pending_from_options_events":"0.00000000",
      "updated_at":"2020-07-24T13:43:49.383902Z",
      "created_at":"2018-04-20T19:04:26.048365Z"
   },
   {
      "url":"https://api.robinhood.com/positions/5QR16506/0eb7aae6-224e-46b9-a855-07c22f7e042c/",
      "symbol":"ZS",
      "instrument":"https://api.robinhood.com/instruments/0eb7aae6-224e-46b9-a855-07c22f7e042c/",
      "account":"https://api.robinhood.com/accounts/5QR16506/",
      "account_number":"5QR16506",
      "average_buy_price":"123.9791",
      "pending_average_buy_price":"123.9791",
      "quantity":"1.67117000",
      "intraday_average_buy_price":"120.4251",
      "intraday_quantity":"0.19929400",
      "shares_held_for_buys":"0.00000000",
      "shares_held_for_sells":"0.00000000",
      "shares_held_for_stock_grants":"0.00000000",
      "shares_held_for_options_collateral":"0.00000000",
      "shares_held_for_options_events":"0.00000000",
      "shares_pending_from_options_events":"0.00000000",
      "updated_at":"2020-07-24T13:44:50.593753Z",
      "created_at":"2020-06-08T13:38:49.747334Z"
   },
   {
      "url":"https://api.robinhood.com/positions/5QR16506/2bee019d-7fb4-40e4-9adb-580a58c136a9/",
      "symbol":"TWLO",
      "instrument":"https://api.robinhood.com/instruments/2bee019d-7fb4-40e4-9adb-580a58c136a9/",
      "account":"https://api.robinhood.com/accounts/5QR16506/",
      "account_number":"5QR16506",
      "average_buy_price":"256.0122",
      "pending_average_buy_price":"256.0122",
      "quantity":"1.40079300",
      "intraday_average_buy_price":"243.1231",
      "intraday_quantity":"0.22375500",
      "shares_held_for_buys":"0.00000000",
      "shares_held_for_sells":"0.00000000",
      "shares_held_for_stock_grants":"0.00000000",
      "shares_held_for_options_collateral":"0.00000000",
      "shares_held_for_options_events":"0.00000000",
      "shares_pending_from_options_events":"0.00000000",
      "updated_at":"2020-07-24T13:55:28.902218Z",
      "created_at":"2020-05-27T15:00:05.887423Z"
   },
   {
      "url":"https://api.robinhood.com/positions/5QR16506/20273240-1f75-4548-aa06-c7b7f3b5d836/",
      "symbol":"CTAS",
      "instrument":"https://api.robinhood.com/instruments/20273240-1f75-4548-aa06-c7b7f3b5d836/",
      "account":"https://api.robinhood.com/accounts/5QR16506/",
      "account_number":"5QR16506",
      "average_buy_price":"294.6111",
      "pending_average_buy_price":"294.6111",
      "quantity":"0.49831800",
      "intraday_average_buy_price":"298.8506",
      "intraday_quantity":"0.06090000",
      "shares_held_for_buys":"0.00000000",
      "shares_held_for_sells":"0.00000000",
      "shares_held_for_stock_grants":"0.00000000",
      "shares_held_for_options_collateral":"0.00000000",
      "shares_held_for_options_events":"0.00000000",
      "shares_pending_from_options_events":"0.00000000",
      "updated_at":"2020-07-24T13:48:17.91305Z",
      "created_at":"2020-06-08T13:41:14.216238Z"
   },
   {
      "url":"https://api.robinhood.com/positions/5QR16506/7aeae03d-a1ba-4670-af0e-b592378e7bfc/",
      "symbol":"AZN",
      "instrument":"https://api.robinhood.com/instruments/7aeae03d-a1ba-4670-af0e-b592378e7bfc/",
      "account":"https://api.robinhood.com/accounts/5QR16506/",
      "account_number":"5QR16506",
      "average_buy_price":"52.8274",
      "pending_average_buy_price":"52.8274",
      "quantity":"19.02931900",
      "intraday_average_buy_price":"0.0000",
      "intraday_quantity":"0.00000000",
      "shares_held_for_buys":"0.00000000",
      "shares_held_for_sells":"0.00000000",
      "shares_held_for_stock_grants":"0.00000000",
      "shares_held_for_options_collateral":"0.00000000",
      "shares_held_for_options_events":"0.00000000",
      "shares_pending_from_options_events":"0.00000000",
      "updated_at":"2020-06-30T13:37:59.000143Z",
      "created_at":"2020-06-08T16:27:46.61528Z"
   },
   {
      "url":"https://api.robinhood.com/positions/5QR16506/186161e4-fb22-4c0f-91bb-786572fc4eb2/",
      "symbol":"TTD",
      "instrument":"https://api.robinhood.com/instruments/186161e4-fb22-4c0f-91bb-786572fc4eb2/",
      "account":"https://api.robinhood.com/accounts/5QR16506/",
      "account_number":"5QR16506",
      "average_buy_price":"431.9813",
      "pending_average_buy_price":"431.9813",
      "quantity":"0.73693000",
      "intraday_average_buy_price":"412.9805",
      "intraday_quantity":"0.10218400",
      "shares_held_for_buys":"0.00000000",
      "shares_held_for_sells":"0.00000000",
      "shares_held_for_stock_grants":"0.00000000",
      "shares_held_for_options_collateral":"0.00000000",
      "shares_held_for_options_events":"0.00000000",
      "shares_pending_from_options_events":"0.00000000",
      "updated_at":"2020-07-24T13:55:30.990326Z",
      "created_at":"2020-06-08T17:03:27.000591Z"
   },
   {
      "url":"https://api.robinhood.com/positions/5QR16506/d57904fb-55fe-4e2b-97f7-34ef2e0729ec/",
      "symbol":"OKTA",
      "instrument":"https://api.robinhood.com/instruments/d57904fb-55fe-4e2b-97f7-34ef2e0729ec/",
      "account":"https://api.robinhood.com/accounts/5QR16506/",
      "account_number":"5QR16506",
      "average_buy_price":"208.0053",
      "pending_average_buy_price":"208.0053",
      "quantity":"1.39996400",
      "intraday_average_buy_price":"201.8629",
      "intraday_quantity":"0.20806200",
      "shares_held_for_buys":"0.00000000",
      "shares_held_for_sells":"0.00000000",
      "shares_held_for_stock_grants":"0.00000000",
      "shares_held_for_options_collateral":"0.00000000",
      "shares_held_for_options_events":"0.00000000",
      "shares_pending_from_options_events":"0.00000000",
      "updated_at":"2020-07-24T13:55:31.13364Z",
      "created_at":"2020-06-08T17:03:48.188849Z"
   },
   {
      "url":"https://api.robinhood.com/positions/5QR16506/5ded081d-81b8-473a-ae17-ca63cbad88eb/",
      "symbol":"FIVN",
      "instrument":"https://api.robinhood.com/instruments/5ded081d-81b8-473a-ae17-ca63cbad88eb/",
      "account":"https://api.robinhood.com/accounts/5QR16506/",
      "account_number":"5QR16506",
      "average_buy_price":"113.8570",
      "pending_average_buy_price":"113.8570",
      "quantity":"1.43732900",
      "intraday_average_buy_price":"109.5550",
      "intraday_quantity":"0.16430100",
      "shares_held_for_buys":"0.00000000",
      "shares_held_for_sells":"0.00000000",
      "shares_held_for_stock_grants":"0.00000000",
      "shares_held_for_options_collateral":"0.00000000",
      "shares_held_for_options_events":"0.00000000",
      "shares_pending_from_options_events":"0.00000000",
      "updated_at":"2020-07-24T13:44:53.487085Z",
      "created_at":"2020-06-08T17:04:09.500451Z"
   },
   {
      "url":"https://api.robinhood.com/positions/5QR16506/a0d233bb-6b00-4b6c-a2f9-2788ce3ce1f6/",
      "symbol":"SPLK",
      "instrument":"https://api.robinhood.com/instruments/a0d233bb-6b00-4b6c-a2f9-2788ce3ce1f6/",
      "account":"https://api.robinhood.com/accounts/5QR16506/",
      "account_number":"5QR16506",
      "average_buy_price":"202.5421",
      "pending_average_buy_price":"202.5421",
      "quantity":"0.76907500",
      "intraday_average_buy_price":"198.2706",
      "intraday_quantity":"0.09078500",
      "shares_held_for_buys":"0.00000000",
      "shares_held_for_sells":"0.00000000",
      "shares_held_for_stock_grants":"0.00000000",
      "shares_held_for_options_collateral":"0.00000000",
      "shares_held_for_options_events":"0.00000000",
      "shares_pending_from_options_events":"0.00000000",
      "updated_at":"2020-07-24T13:45:57.043752Z",
      "created_at":"2020-06-08T17:04:20.110827Z"
   },
   {
      "url":"https://api.robinhood.com/positions/5QR16506/3371ea83-dbf2-4b61-aab6-bc932fb3e78d/",
      "symbol":"COUP",
      "instrument":"https://api.robinhood.com/instruments/3371ea83-dbf2-4b61-aab6-bc932fb3e78d/",
      "account":"https://api.robinhood.com/accounts/5QR16506/",
      "account_number":"5QR16506",
      "average_buy_price":"299.8624",
      "pending_average_buy_price":"299.8624",
      "quantity":"1.37122900",
      "intraday_average_buy_price":"288.7918",
      "intraday_quantity":"0.18837100",
      "shares_held_for_buys":"0.00000000",
      "shares_held_for_sells":"0.00000000",
      "shares_held_for_stock_grants":"0.00000000",
      "shares_held_for_options_collateral":"0.00000000",
      "shares_held_for_options_events":"0.00000000",
      "shares_pending_from_options_events":"0.00000000",
      "updated_at":"2020-07-24T13:54:25.209016Z",
      "created_at":"2020-06-08T17:04:30.772505Z"
   },
   {
      "url":"https://api.robinhood.com/positions/5QR16506/4b4d198e-fe71-487c-8e3b-584732a2bfaa/",
      "symbol":"CRWD",
      "instrument":"https://api.robinhood.com/instruments/4b4d198e-fe71-487c-8e3b-584732a2bfaa/",
      "account":"https://api.robinhood.com/accounts/5QR16506/",
      "account_number":"5QR16506",
      "average_buy_price":"102.0226",
      "pending_average_buy_price":"102.0226",
      "quantity":"3.34435700",
      "intraday_average_buy_price":"98.0831",
      "intraday_quantity":"0.49142000",
      "shares_held_for_buys":"0.00000000",
      "shares_held_for_sells":"0.00000000",
      "shares_held_for_stock_grants":"0.00000000",
      "shares_held_for_options_collateral":"0.00000000",
      "shares_held_for_options_events":"0.00000000",
      "shares_pending_from_options_events":"0.00000000",
      "updated_at":"2020-07-24T13:54:30.404754Z",
      "created_at":"2020-06-08T17:05:56.154886Z"
   },
   {
      "url":"https://api.robinhood.com/positions/5QR16506/258666ba-708c-4126-8625-67c486eca81c/",
      "symbol":"ESTC",
      "instrument":"https://api.robinhood.com/instruments/258666ba-708c-4126-8625-67c486eca81c/",
      "account":"https://api.robinhood.com/accounts/5QR16506/",
      "account_number":"5QR16506",
      "average_buy_price":"91.8239",
      "pending_average_buy_price":"91.8239",
      "quantity":"1.64074900",
      "intraday_average_buy_price":"89.4454",
      "intraday_quantity":"0.20124000",
      "shares_held_for_buys":"0.00000000",
      "shares_held_for_sells":"0.00000000",
      "shares_held_for_stock_grants":"0.00000000",
      "shares_held_for_options_collateral":"0.00000000",
      "shares_held_for_options_events":"0.00000000",
      "shares_pending_from_options_events":"0.00000000",
      "updated_at":"2020-07-24T13:44:53.285557Z",
      "created_at":"2020-06-08T17:05:45.534451Z"
   },
   {
      "url":"https://api.robinhood.com/positions/5QR16506/9c53326c-d07e-4b82-82d2-b108ec5d9530/",
      "symbol":"SPOT",
      "instrument":"https://api.robinhood.com/instruments/9c53326c-d07e-4b82-82d2-b108ec5d9530/",
      "account":"https://api.robinhood.com/accounts/5QR16506/",
      "account_number":"5QR16506",
      "average_buy_price":"273.3474",
      "pending_average_buy_price":"273.3474",
      "quantity":"0.57161700",
      "intraday_average_buy_price":"260.4651",
      "intraday_quantity":"0.06987500",
      "shares_held_for_buys":"0.00000000",
      "shares_held_for_sells":"0.00000000",
      "shares_held_for_stock_grants":"0.00000000",
      "shares_held_for_options_collateral":"0.00000000",
      "shares_held_for_options_events":"0.00000000",
      "shares_pending_from_options_events":"0.00000000",
      "updated_at":"2020-07-24T13:45:56.951074Z",
      "created_at":"2018-05-07T14:08:34.18046Z"
   },
   {
      "url":"https://api.robinhood.com/positions/5QR16506/260c451b-fe7b-430e-bed2-22479ea86cd0/",
      "symbol":"WDAY",
      "instrument":"https://api.robinhood.com/instruments/260c451b-fe7b-430e-bed2-22479ea86cd0/",
      "account":"https://api.robinhood.com/accounts/5QR16506/",
      "account_number":"5QR16506",
      "average_buy_price":"186.4292",
      "pending_average_buy_price":"186.4292",
      "quantity":"0.75578300",
      "intraday_average_buy_price":"183.3070",
      "intraday_quantity":"0.09928700",
      "shares_held_for_buys":"0.00000000",
      "shares_held_for_sells":"0.00000000",
      "shares_held_for_stock_grants":"0.00000000",
      "shares_held_for_options_collateral":"0.00000000",
      "shares_held_for_options_events":"0.00000000",
      "shares_pending_from_options_events":"0.00000000",
      "updated_at":"2020-07-24T13:45:57.447903Z",
      "created_at":"2020-06-09T18:29:33.306476Z"
   },
   {
      "url":"https://api.robinhood.com/positions/5QR16506/cf1d849d-06f7-4374-9e84-13129713d0c7/",
      "symbol":"CRM",
      "instrument":"https://api.robinhood.com/instruments/cf1d849d-06f7-4374-9e84-13129713d0c7/",
      "account":"https://api.robinhood.com/accounts/5QR16506/",
      "account_number":"5QR16506",
      "average_buy_price":"189.7601",
      "pending_average_buy_price":"189.7601",
      "quantity":"1.60149600",
      "intraday_average_buy_price":"185.8261",
      "intraday_quantity":"0.12915300",
      "shares_held_for_buys":"0.00000000",
      "shares_held_for_sells":"0.00000000",
      "shares_held_for_stock_grants":"0.00000000",
      "shares_held_for_options_collateral":"0.00000000",
      "shares_held_for_options_events":"0.00000000",
      "shares_pending_from_options_events":"0.00000000",
      "updated_at":"2020-07-24T13:47:12.084956Z",
      "created_at":"2015-02-25T18:10:10.136128Z"
   },
   {
      "url":"https://api.robinhood.com/positions/5QR16506/809adc21-ef75-4c3d-9c0e-5f9a167f235b/",
      "symbol":"ADBE",
      "instrument":"https://api.robinhood.com/instruments/809adc21-ef75-4c3d-9c0e-5f9a167f235b/",
      "account":"https://api.robinhood.com/accounts/5QR16506/",
      "account_number":"5QR16506",
      "average_buy_price":"437.8845",
      "pending_average_buy_price":"437.8845",
      "quantity":"0.46843400",
      "intraday_average_buy_price":"426.4467",
      "intraday_quantity":"0.05674800",
      "shares_held_for_buys":"0.00000000",
      "shares_held_for_sells":"0.00000000",
      "shares_held_for_stock_grants":"0.00000000",
      "shares_held_for_options_collateral":"0.00000000",
      "shares_held_for_options_events":"0.00000000",
      "shares_pending_from_options_events":"0.00000000",
      "updated_at":"2020-07-24T13:46:08.600452Z",
      "created_at":"2018-03-28T13:33:31.982202Z"
   },
   {
      "url":"https://api.robinhood.com/positions/5QR16506/1790dd4f-a7ff-409e-90de-cad5efafde10/",
      "symbol":"QQQ",
      "instrument":"https://api.robinhood.com/instruments/1790dd4f-a7ff-409e-90de-cad5efafde10/",
      "account":"https://api.robinhood.com/accounts/5QR16506/",
      "account_number":"5QR16506",
      "average_buy_price":"260.2165",
      "pending_average_buy_price":"260.2165",
      "quantity":"4.97439900",
      "intraday_average_buy_price":"253.2156",
      "intraday_quantity":"0.63424200",
      "shares_held_for_buys":"0.00000000",
      "shares_held_for_sells":"0.00000000",
      "shares_held_for_stock_grants":"0.00000000",
      "shares_held_for_options_collateral":"0.00000000",
      "shares_held_for_options_events":"0.00000000",
      "shares_pending_from_options_events":"0.00000000",
      "updated_at":"2020-07-24T13:51:39.730205Z",
      "created_at":"2017-06-29T15:26:37.793066Z"
   },
   {
      "url":"https://api.robinhood.com/positions/5QR16506/8f92e76f-1e0e-4478-8580-16a6ffcfaef5/",
      "symbol":"SPY",
      "instrument":"https://api.robinhood.com/instruments/8f92e76f-1e0e-4478-8580-16a6ffcfaef5/",
      "account":"https://api.robinhood.com/accounts/5QR16506/",
      "account_number":"5QR16506",
      "average_buy_price":"323.7767",
      "pending_average_buy_price":"323.7767",
      "quantity":"3.19760600",
      "intraday_average_buy_price":"320.4223",
      "intraday_quantity":"0.42131900",
      "shares_held_for_buys":"0.00000000",
      "shares_held_for_sells":"0.00000000",
      "shares_held_for_stock_grants":"0.00000000",
      "shares_held_for_options_collateral":"0.00000000",
      "shares_held_for_options_events":"0.00000000",
      "shares_pending_from_options_events":"0.00000000",
      "updated_at":"2020-07-24T13:51:40.404504Z",
      "created_at":"2017-06-29T17:07:13.131592Z"
   },
   {
      "url":"https://api.robinhood.com/positions/5QR16506/bab3b12b-4216-4b01-b2d8-9587ee5f41cf/",
      "symbol":"DIA",
      "instrument":"https://api.robinhood.com/instruments/bab3b12b-4216-4b01-b2d8-9587ee5f41cf/",
      "account":"https://api.robinhood.com/accounts/5QR16506/",
      "account_number":"5QR16506",
      "average_buy_price":"267.5185",
      "pending_average_buy_price":"267.5185",
      "quantity":"3.86111500",
      "intraday_average_buy_price":"265.0910",
      "intraday_quantity":"0.50925900",
      "shares_held_for_buys":"0.00000000",
      "shares_held_for_sells":"0.00000000",
      "shares_held_for_stock_grants":"0.00000000",
      "shares_held_for_options_collateral":"0.00000000",
      "shares_held_for_options_events":"0.00000000",
      "shares_pending_from_options_events":"0.00000000",
      "updated_at":"2020-07-24T13:51:38.530329Z",
      "created_at":"2017-06-29T17:37:57.658452Z"
   },
   {
      "url":"https://api.robinhood.com/positions/5QR16506/698f04e6-1710-4f34-b7af-4a88fe5e47b3/",
      "symbol":"AVGO",
      "instrument":"https://api.robinhood.com/instruments/698f04e6-1710-4f34-b7af-4a88fe5e47b3/",
      "account":"https://api.robinhood.com/accounts/5QR16506/",
      "account_number":"5QR16506",
      "average_buy_price":"310.9324",
      "pending_average_buy_price":"310.9324",
      "quantity":"0.45254200",
      "intraday_average_buy_price":"307.6195",
      "intraday_quantity":"0.05916400",
      "shares_held_for_buys":"0.00000000",
      "shares_held_for_sells":"0.00000000",
      "shares_held_for_stock_grants":"0.00000000",
      "shares_held_for_options_collateral":"0.00000000",
      "shares_held_for_options_events":"0.00000000",
      "shares_pending_from_options_events":"0.00000000",
      "updated_at":"2020-07-24T13:47:12.445984Z",
      "created_at":"2018-03-29T17:18:19.221733Z"
   },
   {
      "url":"https://api.robinhood.com/positions/5QR16506/500a5a3e-1e21-4e1f-b132-d78375894c46/",
      "symbol":"SSO",
      "instrument":"https://api.robinhood.com/instruments/500a5a3e-1e21-4e1f-b132-d78375894c46/",
      "account":"https://api.robinhood.com/accounts/5QR16506/",
      "account_number":"5QR16506",
      "average_buy_price":"137.3092",
      "pending_average_buy_price":"137.3092",
      "quantity":"7.73436900",
      "intraday_average_buy_price":"134.3397",
      "intraday_quantity":"1.63317400",
      "shares_held_for_buys":"0.00000000",
      "shares_held_for_sells":"0.00000000",
      "shares_held_for_stock_grants":"0.00000000",
      "shares_held_for_options_collateral":"0.00000000",
      "shares_held_for_options_events":"0.00000000",
      "shares_pending_from_options_events":"0.00000000",
      "updated_at":"2020-07-24T13:51:39.876541Z",
      "created_at":"2018-10-08T13:44:28.813571Z"
   },
   {
      "url":"https://api.robinhood.com/positions/5QR16506/b1e20cfb-eab0-4f0a-b81f-b17a0dbf92b9/",
      "symbol":"DDM",
      "instrument":"https://api.robinhood.com/instruments/b1e20cfb-eab0-4f0a-b81f-b17a0dbf92b9/",
      "account":"https://api.robinhood.com/accounts/5QR16506/",
      "account_number":"5QR16506",
      "average_buy_price":"43.3544",
      "pending_average_buy_price":"43.3544",
      "quantity":"26.86697400",
      "intraday_average_buy_price":"42.5636",
      "intraday_quantity":"4.86801100",
      "shares_held_for_buys":"0.00000000",
      "shares_held_for_sells":"0.00000000",
      "shares_held_for_stock_grants":"0.00000000",
      "shares_held_for_options_collateral":"0.00000000",
      "shares_held_for_options_events":"0.00000000",
      "shares_pending_from_options_events":"0.00000000",
      "updated_at":"2020-07-24T13:51:39.053412Z",
      "created_at":"2018-12-04T17:22:41.589135Z"
   },
   {
      "url":"https://api.robinhood.com/positions/5QR16506/e5cee1ce-78c0-469b-bc61-c8e0c5c87c70/",
      "symbol":"QLD",
      "instrument":"https://api.robinhood.com/instruments/e5cee1ce-78c0-469b-bc61-c8e0c5c87c70/",
      "account":"https://api.robinhood.com/accounts/5QR16506/",
      "account_number":"5QR16506",
      "average_buy_price":"161.2483",
      "pending_average_buy_price":"161.2483",
      "quantity":"10.97252500",
      "intraday_average_buy_price":"153.1568",
      "intraday_quantity":"1.85692000",
      "shares_held_for_buys":"0.00000000",
      "shares_held_for_sells":"0.00000000",
      "shares_held_for_stock_grants":"0.00000000",
      "shares_held_for_options_collateral":"0.00000000",
      "shares_held_for_options_events":"0.00000000",
      "shares_pending_from_options_events":"0.00000000",
      "updated_at":"2020-07-24T13:51:38.213039Z",
      "created_at":"2019-03-27T15:55:59.367961Z"
   },
   {
      "url":"https://api.robinhood.com/positions/5QR16506/9ff60b7b-3d13-4cb4-ae6b-93249ccb50f8/",
      "symbol":"VEEV",
      "instrument":"https://api.robinhood.com/instruments/9ff60b7b-3d13-4cb4-ae6b-93249ccb50f8/",
      "account":"https://api.robinhood.com/accounts/5QR16506/",
      "account_number":"5QR16506",
      "average_buy_price":"255.0279",
      "pending_average_buy_price":"255.0279",
      "quantity":"0.73290000",
      "intraday_average_buy_price":"247.8955",
      "intraday_quantity":"0.09681500",
      "shares_held_for_buys":"0.00000000",
      "shares_held_for_sells":"0.00000000",
      "shares_held_for_stock_grants":"0.00000000",
      "shares_held_for_options_collateral":"0.00000000",
      "shares_held_for_options_events":"0.00000000",
      "shares_pending_from_options_events":"0.00000000",
      "updated_at":"2020-07-24T13:44:50.426019Z",
      "created_at":"2020-06-11T13:39:15.713425Z"
   },
   {
      "url":"https://api.robinhood.com/positions/5QR16506/4a4bf458-6a5c-4f74-9c5d-1a4b5b08482e/",
      "symbol":"CAT",
      "instrument":"https://api.robinhood.com/instruments/4a4bf458-6a5c-4f74-9c5d-1a4b5b08482e/",
      "account":"https://api.robinhood.com/accounts/5QR16506/",
      "account_number":"5QR16506",
      "average_buy_price":"136.4613",
      "pending_average_buy_price":"136.4613",
      "quantity":"1.13512100",
      "intraday_average_buy_price":"137.8610",
      "intraday_quantity":"0.13201700",
      "shares_held_for_buys":"0.00000000",
      "shares_held_for_sells":"0.00000000",
      "shares_held_for_stock_grants":"0.00000000",
      "shares_held_for_options_collateral":"0.00000000",
      "shares_held_for_options_events":"0.00000000",
      "shares_pending_from_options_events":"0.00000000",
      "updated_at":"2020-07-24T13:48:13.595556Z",
      "created_at":"2018-01-25T15:00:40.353449Z"
   },
   {
      "url":"https://api.robinhood.com/positions/5QR16506/e5e9b095-0dd8-4813-8cec-dc41beac9743/",
      "symbol":"HEI",
      "instrument":"https://api.robinhood.com/instruments/e5e9b095-0dd8-4813-8cec-dc41beac9743/",
      "account":"https://api.robinhood.com/accounts/5QR16506/",
      "account_number":"5QR16506",
      "average_buy_price":"98.6201",
      "pending_average_buy_price":"98.6201",
      "quantity":"0.61042300",
      "intraday_average_buy_price":"0.0000",
      "intraday_quantity":"0.00000000",
      "shares_held_for_buys":"0.00000000",
      "shares_held_for_sells":"0.00000000",
      "shares_held_for_stock_grants":"0.00000000",
      "shares_held_for_options_collateral":"0.00000000",
      "shares_held_for_options_events":"0.00000000",
      "shares_pending_from_options_events":"0.00000000",
      "updated_at":"2020-07-23T14:28:36.72274Z",
      "created_at":"2019-12-17T15:41:11.243624Z"
   },
   {
      "url":"https://api.robinhood.com/positions/5QR16506/279d787b-515b-4f9c-a684-45f92afb557f/",
      "symbol":"ROKU",
      "instrument":"https://api.robinhood.com/instruments/279d787b-515b-4f9c-a684-45f92afb557f/",
      "account":"https://api.robinhood.com/accounts/5QR16506/",
      "account_number":"5QR16506",
      "average_buy_price":"151.6732",
      "pending_average_buy_price":"151.6732",
      "quantity":"2.63935800",
      "intraday_average_buy_price":"147.2090",
      "intraday_quantity":"0.36818400",
      "shares_held_for_buys":"0.00000000",
      "shares_held_for_sells":"0.00000000",
      "shares_held_for_stock_grants":"0.00000000",
      "shares_held_for_options_collateral":"0.00000000",
      "shares_held_for_options_events":"0.00000000",
      "shares_pending_from_options_events":"0.00000000",
      "updated_at":"2020-07-24T13:54:27.516525Z",
      "created_at":"2020-02-21T15:10:26.102538Z"
   },
   {
      "url":"https://api.robinhood.com/positions/5QR16506/9722f34e-b765-410d-9d42-06d30b3ebe70/",
      "symbol":"NET",
      "instrument":"https://api.robinhood.com/instruments/9722f34e-b765-410d-9d42-06d30b3ebe70/",
      "account":"https://api.robinhood.com/accounts/5QR16506/",
      "account_number":"5QR16506",
      "average_buy_price":"37.0535",
      "pending_average_buy_price":"37.0535",
      "quantity":"3.99423200",
      "intraday_average_buy_price":"35.7847",
      "intraday_quantity":"0.50859700",
      "shares_held_for_buys":"0.00000000",
      "shares_held_for_sells":"0.00000000",
      "shares_held_for_stock_grants":"0.00000000",
      "shares_held_for_options_collateral":"0.00000000",
      "shares_held_for_options_events":"0.00000000",
      "shares_pending_from_options_events":"0.00000000",
      "updated_at":"2020-07-24T13:44:54.815383Z",
      "created_at":"2020-06-18T13:32:42.785631Z"
   },
   {
      "url":"https://api.robinhood.com/positions/5QR16506/2346aaa6-b39f-480c-a42c-58134a6f349a/",
      "symbol":"FTNT",
      "instrument":"https://api.robinhood.com/instruments/2346aaa6-b39f-480c-a42c-58134a6f349a/",
      "account":"https://api.robinhood.com/accounts/5QR16506/",
      "account_number":"5QR16506",
      "average_buy_price":"134.2875",
      "pending_average_buy_price":"134.2875",
      "quantity":"1.09980400",
      "intraday_average_buy_price":"131.3523",
      "intraday_quantity":"0.13703600",
      "shares_held_for_buys":"0.00000000",
      "shares_held_for_sells":"0.00000000",
      "shares_held_for_stock_grants":"0.00000000",
      "shares_held_for_options_collateral":"0.00000000",
      "shares_held_for_options_events":"0.00000000",
      "shares_pending_from_options_events":"0.00000000",
      "updated_at":"2020-07-24T13:44:54.367503Z",
      "created_at":"2020-06-18T13:32:48.005009Z"
   },
   {
      "url":"https://api.robinhood.com/positions/5QR16506/1de794e3-c447-4125-b3d9-6bcb4895444c/",
      "symbol":"RTX",
      "instrument":"https://api.robinhood.com/instruments/1de794e3-c447-4125-b3d9-6bcb4895444c/",
      "account":"https://api.robinhood.com/accounts/5QR16506/",
      "account_number":"5QR16506",
      "average_buy_price":"63.2943",
      "pending_average_buy_price":"63.2943",
      "quantity":"2.46467400",
      "intraday_average_buy_price":"63.8102",
      "intraday_quantity":"0.28522100",
      "shares_held_for_buys":"0.00000000",
      "shares_held_for_sells":"0.00000000",
      "shares_held_for_stock_grants":"0.00000000",
      "shares_held_for_options_collateral":"0.00000000",
      "shares_held_for_options_events":"0.00000000",
      "shares_pending_from_options_events":"0.00000000",
      "updated_at":"2020-07-24T13:49:18.261205Z",
      "created_at":"2020-06-18T13:36:44.998443Z"
   },
   {
      "url":"https://api.robinhood.com/positions/5QR16506/f69573b8-d80a-4df9-9c36-4fdd2be5c70f/",
      "symbol":"AYX",
      "instrument":"https://api.robinhood.com/instruments/f69573b8-d80a-4df9-9c36-4fdd2be5c70f/",
      "account":"https://api.robinhood.com/accounts/5QR16506/",
      "account_number":"5QR16506",
      "average_buy_price":"165.1519",
      "pending_average_buy_price":"165.1519",
      "quantity":"2.42770400",
      "intraday_average_buy_price":"159.7326",
      "intraday_quantity":"0.33806500",
      "shares_held_for_buys":"0.00000000",
      "shares_held_for_sells":"0.00000000",
      "shares_held_for_stock_grants":"0.00000000",
      "shares_held_for_options_collateral":"0.00000000",
      "shares_held_for_options_events":"0.00000000",
      "shares_pending_from_options_events":"0.00000000",
      "updated_at":"2020-07-24T13:54:24.77365Z",
      "created_at":"2020-06-19T13:35:49.144332Z"
   },
   {
      "url":"https://api.robinhood.com/positions/5QR16506/2291271f-15ee-4438-b067-b0b8079c47e1/",
      "symbol":"VRM",
      "instrument":"https://api.robinhood.com/instruments/2291271f-15ee-4438-b067-b0b8079c47e1/",
      "account":"https://api.robinhood.com/accounts/5QR16506/",
      "account_number":"5QR16506",
      "average_buy_price":"49.1228",
      "pending_average_buy_price":"49.1228",
      "quantity":"3.87600200",
      "intraday_average_buy_price":"47.7700",
      "intraday_quantity":"0.62800900",
      "shares_held_for_buys":"0.00000000",
      "shares_held_for_sells":"0.00000000",
      "shares_held_for_stock_grants":"0.00000000",
      "shares_held_for_options_collateral":"0.00000000",
      "shares_held_for_options_events":"0.00000000",
      "shares_pending_from_options_events":"0.00000000",
      "updated_at":"2020-07-24T13:55:29.899462Z",
      "created_at":"2020-06-24T17:31:40.647762Z"
   },
   {
      "url":"https://api.robinhood.com/positions/5QR16506/6e557a62-6956-4341-8f48-d39d560dc408/",
      "symbol":"PINS",
      "instrument":"https://api.robinhood.com/instruments/6e557a62-6956-4341-8f48-d39d560dc408/",
      "account":"https://api.robinhood.com/accounts/5QR16506/",
      "account_number":"5QR16506",
      "average_buy_price":"24.8611",
      "pending_average_buy_price":"24.8611",
      "quantity":"4.62570300",
      "intraday_average_buy_price":"23.6600",
      "intraday_quantity":"0.76923000",
      "shares_held_for_buys":"0.00000000",
      "shares_held_for_sells":"0.00000000",
      "shares_held_for_stock_grants":"0.00000000",
      "shares_held_for_options_collateral":"0.00000000",
      "shares_held_for_options_events":"0.00000000",
      "shares_pending_from_options_events":"0.00000000",
      "updated_at":"2020-07-24T13:56:32.983768Z",
      "created_at":"2020-06-25T15:02:13.122551Z"
   },
   {
      "url":"https://api.robinhood.com/positions/5QR16506/7764062c-8ae7-4a74-8d61-e66ffe21697f/",
      "symbol":"ETSY",
      "instrument":"https://api.robinhood.com/instruments/7764062c-8ae7-4a74-8d61-e66ffe21697f/",
      "account":"https://api.robinhood.com/accounts/5QR16506/",
      "account_number":"5QR16506",
      "average_buy_price":"103.3291",
      "pending_average_buy_price":"103.3291",
      "quantity":"1.47683400",
      "intraday_average_buy_price":"99.9253",
      "intraday_quantity":"0.24218100",
      "shares_held_for_buys":"0.00000000",
      "shares_held_for_sells":"0.00000000",
      "shares_held_for_stock_grants":"0.00000000",
      "shares_held_for_options_collateral":"0.00000000",
      "shares_held_for_options_events":"0.00000000",
      "shares_pending_from_options_events":"0.00000000",
      "updated_at":"2020-07-24T13:55:30.089428Z",
      "created_at":"2020-07-08T17:25:21.184978Z"
   },
   {
      "url":"https://api.robinhood.com/positions/5QR16506/90e14bc4-eb74-404c-8b61-00a2a6165e4f/",
      "symbol":"FOUR",
      "instrument":"https://api.robinhood.com/instruments/90e14bc4-eb74-404c-8b61-00a2a6165e4f/",
      "account":"https://api.robinhood.com/accounts/5QR16506/",
      "account_number":"5QR16506",
      "average_buy_price":"36.0854",
      "pending_average_buy_price":"36.0854",
      "quantity":"4.23993900",
      "intraday_average_buy_price":"35.0250",
      "intraday_quantity":"0.69093500",
      "shares_held_for_buys":"0.00000000",
      "shares_held_for_sells":"0.00000000",
      "shares_held_for_stock_grants":"0.00000000",
      "shares_held_for_options_collateral":"0.00000000",
      "shares_held_for_options_events":"0.00000000",
      "shares_pending_from_options_events":"0.00000000",
      "updated_at":"2020-07-24T13:55:31.277301Z",
      "created_at":"2020-07-08T17:25:21.432011Z"
   },
   {
      "url":"https://api.robinhood.com/positions/5QR16506/4b718eba-ea2b-48bf-b0d1-6880c15cc539/",
      "symbol":"API",
      "instrument":"https://api.robinhood.com/instruments/4b718eba-ea2b-48bf-b0d1-6880c15cc539/",
      "account":"https://api.robinhood.com/accounts/5QR16506/",
      "account_number":"5QR16506",
      "average_buy_price":"45.8174",
      "pending_average_buy_price":"45.8174",
      "quantity":"12.00418000",
      "intraday_average_buy_price":"43.3911",
      "intraday_quantity":"1.15230900",
      "shares_held_for_buys":"0.00000000",
      "shares_held_for_sells":"0.00000000",
      "shares_held_for_stock_grants":"0.00000000",
      "shares_held_for_options_collateral":"0.00000000",
      "shares_held_for_options_events":"0.00000000",
      "shares_pending_from_options_events":"0.00000000",
      "updated_at":"2020-07-24T14:50:09.345835Z",
      "created_at":"2020-07-10T14:30:48.346293Z"
   },
   {
      "url":"https://api.robinhood.com/positions/5QR16506/d23d1b81-3efb-4470-ab2e-ba2ac8f0e14f/",
      "symbol":"EVRI",
      "instrument":"https://api.robinhood.com/instruments/d23d1b81-3efb-4470-ab2e-ba2ac8f0e14f/",
      "account":"https://api.robinhood.com/accounts/5QR16506/",
      "account_number":"5QR16506",
      "average_buy_price":"5.9993",
      "pending_average_buy_price":"5.9993",
      "quantity":"9.20100600",
      "intraday_average_buy_price":"0.0000",
      "intraday_quantity":"0.00000000",
      "shares_held_for_buys":"0.00000000",
      "shares_held_for_sells":"0.00000000",
      "shares_held_for_stock_grants":"0.00000000",
      "shares_held_for_options_collateral":"0.00000000",
      "shares_held_for_options_events":"0.00000000",
      "shares_pending_from_options_events":"0.00000000",
      "updated_at":"2020-07-23T14:28:38.209648Z",
      "created_at":"2020-06-04T19:57:22.313307Z"
   },
   {
      "url":"https://api.robinhood.com/positions/5QR16506/ad1edbfb-19c8-4939-be66-1f09bd65b902/",
      "symbol":"WMT",
      "instrument":"https://api.robinhood.com/instruments/ad1edbfb-19c8-4939-be66-1f09bd65b902/",
      "account":"https://api.robinhood.com/accounts/5QR16506/",
      "account_number":"5QR16506",
      "average_buy_price":"132.1951",
      "pending_average_buy_price":"132.1951",
      "quantity":"1.16418900",
      "intraday_average_buy_price":"131.6656",
      "intraday_quantity":"0.13671000",
      "shares_held_for_buys":"0.00000000",
      "shares_held_for_sells":"0.00000000",
      "shares_held_for_stock_grants":"0.00000000",
      "shares_held_for_options_collateral":"0.00000000",
      "shares_held_for_options_events":"0.00000000",
      "shares_pending_from_options_events":"0.00000000",
      "updated_at":"2020-07-24T13:49:19.368341Z",
      "created_at":"2020-07-16T14:22:46.85784Z"
   },
   {
      "url":"https://api.robinhood.com/positions/5QR16506/b26ec3ce-e0b5-4514-b599-b30e0bfd3460/",
      "symbol":"NCNO",
      "instrument":"https://api.robinhood.com/instruments/b26ec3ce-e0b5-4514-b599-b30e0bfd3460/",
      "account":"https://api.robinhood.com/accounts/5QR16506/",
      "account_number":"5QR16506",
      "average_buy_price":"73.6877",
      "pending_average_buy_price":"73.6877",
      "quantity":"3.60711200",
      "intraday_average_buy_price":"73.3852",
      "intraday_quantity":"0.40880200",
      "shares_held_for_buys":"0.00000000",
      "shares_held_for_sells":"0.00000000",
      "shares_held_for_stock_grants":"0.00000000",
      "shares_held_for_options_collateral":"0.00000000",
      "shares_held_for_options_events":"0.00000000",
      "shares_pending_from_options_events":"0.00000000",
      "updated_at":"2020-07-24T13:54:26.627461Z",
      "created_at":"2020-07-21T14:23:38.079134Z"
   },
   {
      "url":"https://api.robinhood.com/positions/5QR16506/a8af0330-cd9c-44c6-9ba5-077521dd4829/",
      "symbol":"ZI",
      "instrument":"https://api.robinhood.com/instruments/a8af0330-cd9c-44c6-9ba5-077521dd4829/",
      "account":"https://api.robinhood.com/accounts/5QR16506/",
      "account_number":"5QR16506",
      "average_buy_price":"41.6350",
      "pending_average_buy_price":"41.6350",
      "quantity":"12.00912600",
      "intraday_average_buy_price":"0.0000",
      "intraday_quantity":"0.00000000",
      "shares_held_for_buys":"0.00000000",
      "shares_held_for_sells":"0.00000000",
      "shares_held_for_stock_grants":"0.00000000",
      "shares_held_for_options_collateral":"0.00000000",
      "shares_held_for_options_events":"0.00000000",
      "shares_pending_from_options_events":"0.00000000",
      "updated_at":"2020-07-22T16:21:34.191702Z",
      "created_at":"2020-07-22T16:21:32.0916Z"
   },
   {
      "url":"https://api.robinhood.com/positions/5QR16506/b797b449-0bcc-46a5-b208-d9245ad33414/",
      "symbol":"IWO",
      "instrument":"https://api.robinhood.com/instruments/b797b449-0bcc-46a5-b208-d9245ad33414/",
      "account":"https://api.robinhood.com/accounts/5QR16506/",
      "account_number":"5QR16506",
      "average_buy_price":"214.8635",
      "pending_average_buy_price":"214.8635",
      "quantity":"1.38180800",
      "intraday_average_buy_price":"210.6331",
      "intraday_quantity":"0.28580500",
      "shares_held_for_buys":"0.00000000",
      "shares_held_for_sells":"0.00000000",
      "shares_held_for_stock_grants":"0.00000000",
      "shares_held_for_options_collateral":"0.00000000",
      "shares_held_for_options_events":"0.00000000",
      "shares_pending_from_options_events":"0.00000000",
      "updated_at":"2020-07-24T13:51:40.019056Z",
      "created_at":"2020-07-23T16:12:31.758478Z"
   },
   {
      "url":"https://api.robinhood.com/positions/5QR16506/91f7ea28-e413-4ca4-b9fa-91f5822f8b8d/",
      "symbol":"TQQQ",
      "instrument":"https://api.robinhood.com/instruments/91f7ea28-e413-4ca4-b9fa-91f5822f8b8d/",
      "account":"https://api.robinhood.com/accounts/5QR16506/",
      "account_number":"5QR16506",
      "average_buy_price":"110.6573",
      "pending_average_buy_price":"110.6573",
      "quantity":"2.79150100",
      "intraday_average_buy_price":"102.0664",
      "intraday_quantity":"0.47420100",
      "shares_held_for_buys":"0.00000000",
      "shares_held_for_sells":"0.00000000",
      "shares_held_for_stock_grants":"0.00000000",
      "shares_held_for_options_collateral":"0.00000000",
      "shares_held_for_options_events":"0.00000000",
      "shares_pending_from_options_events":"0.00000000",
      "updated_at":"2020-07-24T13:52:40.850068Z",
      "created_at":"2020-07-23T16:13:34.402004Z"
   },
   {
      "url":"https://api.robinhood.com/positions/5QR16506/496d6d63-a93d-4693-a5b5-d1e0a72d854f/",
      "symbol":"SPXL",
      "instrument":"https://api.robinhood.com/instruments/496d6d63-a93d-4693-a5b5-d1e0a72d854f/",
      "account":"https://api.robinhood.com/accounts/5QR16506/",
      "account_number":"5QR16506",
      "average_buy_price":"48.0474",
      "pending_average_buy_price":"48.0474",
      "quantity":"4.09179700",
      "intraday_average_buy_price":"46.4427",
      "intraday_quantity":"0.77514900",
      "shares_held_for_buys":"0.00000000",
      "shares_held_for_sells":"0.00000000",
      "shares_held_for_stock_grants":"0.00000000",
      "shares_held_for_options_collateral":"0.00000000",
      "shares_held_for_options_events":"0.00000000",
      "shares_pending_from_options_events":"0.00000000",
      "updated_at":"2020-07-24T13:52:41.775264Z",
      "created_at":"2020-07-23T16:13:34.697612Z"
   },
   {
      "url":"https://api.robinhood.com/positions/5QR16506/e825dd3d-b3d3-4e7a-99ab-d3c38bfdbaaf/",
      "symbol":"UDOW",
      "instrument":"https://api.robinhood.com/instruments/e825dd3d-b3d3-4e7a-99ab-d3c38bfdbaaf/",
      "account":"https://api.robinhood.com/accounts/5QR16506/",
      "account_number":"5QR16506",
      "average_buy_price":"69.9957",
      "pending_average_buy_price":"69.9957",
      "quantity":"2.78588600",
      "intraday_average_buy_price":"68.1174",
      "intraday_quantity":"0.52849900",
      "shares_held_for_buys":"0.00000000",
      "shares_held_for_sells":"0.00000000",
      "shares_held_for_stock_grants":"0.00000000",
      "shares_held_for_options_collateral":"0.00000000",
      "shares_held_for_options_events":"0.00000000",
      "shares_pending_from_options_events":"0.00000000",
      "updated_at":"2020-07-24T13:52:42.11479Z",
      "created_at":"2020-07-23T16:13:34.993885Z"
   }
]